chandra_pypi_demo-0.1.0.dist-info/licenses/LICENSE
demo_package/__init__.py
demo_package/calculator.py
demo_package/greeter.py
chandra_pypi_demo-0.1.0.dist-info/METADATA
chandra_pypi_demo-0.1.0.dist-info/WHEEL
chandra_pypi_demo-0.1.0.dist-info/top_level.txt
chandra_pypi_demo-0.1.0.dist-info/RECORD
