Metadata-Version: 2.4
Name: chandra-pypi-demo
Version: 0.1.0
Summary: A sample Python package demonstrating PyPI publishing
Author-email: Chandra <chandra385123@gmail.com>
Maintainer-email: Chandra <chandra385123@gmail.com>
License: MIT
Project-URL: Homepage, https://github.com/imchandra11/chandra-pypi-demo
Project-URL: Documentation, https://github.com/imchandra11/chandra-pypi-demo#readme
Project-URL: Repository, https://github.com/imchandra11/chandra-pypi-demo
Project-URL: Issues, https://github.com/imchandra11/chandra-pypi-demo/issues
Keywords: demo,example,pypi,tutorial
Classifier: Development Status :: 3 - Alpha
Classifier: Intended Audience :: Developers
Classifier: License :: OSI Approved :: MIT License
Classifier: Programming Language :: Python :: 3
Classifier: Programming Language :: Python :: 3.7
Classifier: Programming Language :: Python :: 3.8
Classifier: Programming Language :: Python :: 3.9
Classifier: Programming Language :: Python :: 3.10
Classifier: Programming Language :: Python :: 3.11
Classifier: Programming Language :: Python :: 3.12
Classifier: Topic :: Software Development :: Libraries :: Python Modules
Requires-Python: >=3.7
License-File: LICENSE
Dynamic: license-file
